SpheroidAnalyzer/__init__.py
SpheroidAnalyzer-0.0.0.dist-info/METADATA
SpheroidAnalyzer-0.0.0.dist-info/WHEEL
SpheroidAnalyzer-0.0.0.dist-info/top_level.txt
SpheroidAnalyzer-0.0.0.dist-info/RECORD
