Metadata-Version: 2.1
Name: SpheroidAnalyzer
Version: 0.0.0
Summary: Coming soon
Author-email: Test Name <a.asaf.lk@gmail.com>
